api4jenkins/__init__.py
api4jenkins/__version__.py
api4jenkins/artifact.py
api4jenkins/build.py
api4jenkins/credential.py
api4jenkins/exceptions.py
api4jenkins/http.py
api4jenkins/input.py
api4jenkins/item.py
api4jenkins/job.py
api4jenkins/mix.py
api4jenkins/node.py
api4jenkins/plugin.py
api4jenkins/queue.py
api4jenkins/report.py
api4jenkins/system.py
api4jenkins/user.py
api4jenkins/view.py
api4jenkins-2.1.0.dist-info/licenses/LICENSE
api4jenkins-2.1.0.dist-info/METADATA
api4jenkins-2.1.0.dist-info/WHEEL
api4jenkins-2.1.0.dist-info/top_level.txt
api4jenkins-2.1.0.dist-info/RECORD
