Metadata-Version: 2.4
Name: api4jenkins
Version: 2.1.0
Summary: Jenkins Python Client
Home-page: https://github.com/joelee2012/api4jenkins
Author: Joe Lee
Author-email: lj_2005@163.com
License: Apache 2.0
Project-URL: Documentation, https://api4jenkins.readthedocs.io
Project-URL: Source, https://github.com/joelee2012/api4jenkins
Keywords: RESTAPI,Jenkins
Classifier: Development Status :: 5 - Production/Stable
Classifier: Intended Audience :: Developers
Classifier: Intended Audience :: System Administrators
Classifier: License :: OSI Approved :: Apache Software License
Classifier: Operating System :: OS Independent
Classifier: Programming Language :: Python
Classifier: Programming Language :: Python :: 3
Classifier: Programming Language :: Python :: 3.8
Classifier: Programming Language :: Python :: 3.9
Classifier: Programming Language :: Python :: 3.10
Classifier: Programming Language :: Python :: 3.11
Classifier: Programming Language :: Python :: 3.12
Classifier: Topic :: Utilities
Requires-Python: >=3.8
License-File: LICENSE
Requires-Dist: httpx>=0.24.1
Dynamic: author
Dynamic: author-email
Dynamic: classifier
Dynamic: description
Dynamic: description-content-type
Dynamic: home-page
Dynamic: keywords
Dynamic: license
Dynamic: license-file
Dynamic: project-url
Dynamic: requires-dist
Dynamic: requires-python
Dynamic: summary
